picasso/__init__.py
picasso/style_composer.py
picasso/style_decorator.py
picasso/style_formatter.py
picasso/exceptions/__init__.py
picasso/exceptions/style_exceptions.py
picasso/loader/__init__.py
picasso/loader/progress_loader.py
picasso/utility/__init__.py
picasso/utility/color_converter.py
picasso/utility/validator.py
picassocli-1.1.3.dist-info/LICENSE
picassocli-1.1.3.dist-info/METADATA
picassocli-1.1.3.dist-info/WHEEL
picassocli-1.1.3.dist-info/top_level.txt
picassocli-1.1.3.dist-info/RECORD
