Metadata-Version: 2.1
Name: picassocli
Version: 1.1.3
Summary: A utility for constructing ANSI escape codes for terminal text styling.
Home-page: https://www.github.com/devinci-it/picassocli
Author: devinci-it
Classifier: Programming Language :: Python :: 3
Classifier: License :: OSI Approved :: MIT License
Classifier: Operating System :: OS Independent
Classifier: Intended Audience :: Developers
Classifier: Topic :: Software Development :: Libraries :: Python Modules
Requires-Python: >=3.6
License-File: LICENSE
Requires-Dist: huefy
